grogupy/__init__.py
grogupy/_tqdm.py
grogupy/config.py
grogupy/_core/__init__.py
grogupy/_core/constants.py
grogupy/_core/cpu_solvers.py
grogupy/_core/gpu_solvers.py
grogupy/_core/utilities.py
grogupy/_core/tests/test_utilities.py
grogupy/batch/__init__.py
grogupy/batch/converge.py
grogupy/batch/timing.py
grogupy/cli/__init__.py
grogupy/cli/analyze.py
grogupy/cli/check_convergence.py
grogupy/cli/run.py
grogupy/cli/tests/convergence1.py
grogupy/cli/tests/convergence2.py
grogupy/cli/tests/input0.fdf
grogupy/cli/tests/input0.py
grogupy/cli/tests/input0_k.fdf
grogupy/cli/tests/input0_k.py
grogupy/cli/tests/input1.fdf
grogupy/cli/tests/input1.py
grogupy/cli/tests/input1_k.fdf
grogupy/cli/tests/input1_k.py
grogupy/cli/tests/input2.fdf
grogupy/cli/tests/input2.py
grogupy/cli/tests/input2_k.fdf
grogupy/cli/tests/input2_k.py
grogupy/cli/tests/input3.fdf
grogupy/cli/tests/input3.py
grogupy/cli/tests/input3_k.fdf
grogupy/cli/tests/input3_k.py
grogupy/cli/tests/input_non_eval.fdf
grogupy/cli/tests/input_non_eval.py
grogupy/cli/tests/test_cli.py
grogupy/io/__init__.py
grogupy/io/io.py
grogupy/io/utilities.py
grogupy/io/tests/test_io.py
grogupy/io/tests/test_io_utilities.py
grogupy/physics/__init__.py
grogupy/physics/builder.py
grogupy/physics/contour.py
grogupy/physics/hamiltonian.py
grogupy/physics/kspace.py
grogupy/physics/magnetic_entity.py
grogupy/physics/pair.py
grogupy/physics/utilities.py
grogupy/physics/tests/test_builder.py
grogupy/physics/tests/test_contour.py
grogupy/physics/tests/test_hamiltonian.py
grogupy/physics/tests/test_kspace.py
grogupy/physics/tests/test_magnetic_entity.py
grogupy/physics/tests/test_pairs.py
grogupy/physics/tests/test_physics_utilities.py
grogupy/viz/__init__.py
grogupy/viz/plotters.py
grogupy/viz/test/test_viz.py
grogupy-0.2.1.dist-info/METADATA
grogupy-0.2.1.dist-info/WHEEL
grogupy-0.2.1.dist-info/entry_points.txt
grogupy-0.2.1.dist-info/licenses/LICENSE
grogupy-0.2.1.dist-info/RECORD
