Metadata-Version: 2.4
Name: grogupy
Version: 0.2.1
Summary: Python package calculating relativistic magnetic interactions  for the generalised Heisenberg model.
Project-URL: Homepage, https://grogupy.readthedocs.io/
Project-URL: Documentation, https://grogupy.readthedocs.io/
Project-URL: Repository, https://github.com/danielpozsar/grogupy
Project-URL: Issues, https://github.com/danielpozsar/grogupy/issues
Author-email: Daniel Tibor Pozsar <danielpozsar@student.elte.hu>, Laszlo Oroszlany <laszlo.oroszlany@ttk.elte.hu>
License-Expression: MIT
License-File: LICENSE
Classifier: Development Status :: 4 - Beta
Classifier: Environment :: GPU :: NVIDIA CUDA :: 12
Classifier: Intended Audience :: Science/Research
Classifier: License :: OSI Approved :: MIT License
Classifier: Natural Language :: English
Classifier: Operating System :: OS Independent
Classifier: Programming Language :: Python :: 3 :: Only
Classifier: Programming Language :: Python :: 3.9
Classifier: Programming Language :: Python :: 3.10
Classifier: Programming Language :: Python :: 3.11
Classifier: Programming Language :: Python :: 3.12
Classifier: Programming Language :: Python :: 3.13
Classifier: Programming Language :: Python :: 3.14
Classifier: Topic :: Scientific/Engineering :: Physics
Requires-Python: >=3.9
Requires-Dist: netcdf4
Requires-Dist: numpy
Requires-Dist: openmpi
Requires-Dist: scipy
Requires-Dist: sisl
Provides-Extra: gpu
Requires-Dist: cupy-cuda12x; extra == 'gpu'
Provides-Extra: mpi
Requires-Dist: mpi4py; extra == 'mpi'
Provides-Extra: viz
Requires-Dist: nbconvert; extra == 'viz'
Requires-Dist: plotly; extra == 'viz'
